[
  {
    "id": "1775108742565",
    "user": "hola",
    "bot": "¡Hola! ¿En qué puedo ayudarte?",
    "timestamp": "2026-04-02T05:45:42.565Z"
  },
  {
    "id": "1775108757311",
    "user": "hola",
    "bot": "¡Hola! ¿En qué puedo ayudarte?",
    "timestamp": "2026-04-02T05:45:57.311Z"
  },
  {
    "id": "1775108757781",
    "user": "hola",
    "bot": "¡Hola! ¿En qué puedo ayudarte?",
    "timestamp": "2026-04-02T05:45:57.781Z"
  },
  {
    "id": "8c0e7eb4-7f1a-4038-a7bc-e66127a50311",
    "user": "hola",
    "bot": "¡Hola! ¿En qué puedo ayudarte?",
    "timestamp": "2026-04-06T05:17:54.608Z"
  },
  {
    "id": "f172973c-5915-41e2-b60a-d4ec661fca9f",
    "user": "hola",
    "bot": "¡Hola! ¿En qué puedo ayudarte?",
    "timestamp": "2026-04-06T05:17:56.611Z"
  },
  {
    "id": "15155cd5-c366-4c63-aacd-3f64bcc163d7",
    "user": "hola",
    "bot": "¡Hola! ¿En qué puedo ayudarte?",
    "timestamp": "2026-04-06T05:17:57.167Z"
  },
  {
    "id": "9f7bb56d-924a-4b39-9102-5108d83554e5",
    "user": "hola",
    "bot": "¡Hola! ¿En qué puedo ayudarte?",
    "timestamp": "2026-04-06T05:25:24.138Z"
  },
  {
    "id": "69d673cd-bba1-4519-98ec-3528e70adda1",
    "user": "hola",
    "bot": "¡Hola! ¿En qué puedo ayudarte?",
    "timestamp": "2026-04-06T05:25:36.586Z"
  },
  {
    "id": "e8f1091b-c8b5-4ada-acf6-aa2e6da43233",
    "user": "hola",
    "bot": "¡Hola! ¿En qué puedo ayudarte?",
    "timestamp": "2026-04-06T05:51:56.092Z"
  },
  {
    "id": "c29b63b7-321d-4560-8de5-0b188481f88c",
    "user": "hola",
    "bot": "¡Hola! ¿En qué puedo ayudarte?",
    "timestamp": "2026-04-06T05:52:08.830Z"
  },
  {
    "id": "2125d5ed-b765-46f5-872b-2970efe203d4",
    "user": "hola",
    "bot": "¡Hola de nuevo! ¿En qué puedo ayudarte de nuevo?",
    "timestamp": "2026-04-06T06:39:39.869Z"
  },
  {
    "id": "ecb6e800-e40c-49e0-831f-b2671ed84ce2",
    "user": "hola",
    "bot": "¡Hola de nuevo! ¿En qué puedo ayudarte de nuevo?",
    "timestamp": "2026-04-06T06:39:42.634Z"
  },
  {
    "id": "4b2310f9-a1d2-4897-b236-b183e797ad1d",
    "user": "como estas",
    "bot": "🤖Lo siento, no entiendo tu mensaje. ¿Puedes reformularlo?",
    "timestamp": "2026-04-06T06:39:57.691Z"
  },
  {
    "id": "5d635c02-af4c-4335-bd3d-6f370b9163ea",
    "user": "cómo estás",
    "bot": "¡Estoy bien, gracias por preguntar! ¿Y tú?",
    "timestamp": "2026-04-06T06:40:13.101Z"
  },
  {
    "id": "be3e7e0f-b3a6-422a-bb8e-699e87dbef5c",
    "user": "bien",
    "bot": "🤖Lo siento, no entiendo tu mensaje. ¿Puedes reformularlo?",
    "timestamp": "2026-04-06T06:40:24.607Z"
  },
  {
    "id": "c8884ccf-111a-4a4a-982c-5f8fe30f716b",
    "user": "y yo",
    "bot": "No estoy seguro a qué te refieres 🤔",
    "timestamp": "2026-04-06T06:40:31.718Z"
  },
  {
    "id": "ea56fad8-8585-48f6-b945-438cfed55bcf",
    "user": "hola",
    "bot": "¡Hola de nuevo! ¿En qué puedo ayudarte de nuevo?",
    "timestamp": "2026-04-06T06:40:45.115Z"
  },
  {
    "id": "6c0ed0be-ae27-4882-b08a-bc0555c6571f",
    "user": "cómo estás",
    "bot": "¡Estoy bien, gracias por preguntar! ¿Y tú?",
    "timestamp": "2026-04-06T06:40:59.765Z"
  },
  {
    "id": "722c1f52-1c9a-4152-aa56-7bdfabb253ca",
    "user": "y yo",
    "bot": "¡Seguro que estás bien también! 😄",
    "timestamp": "2026-04-06T06:41:06.340Z"
  },
  {
    "id": "3ea4f515-e493-4dcb-8411-b35bdfbec22f",
    "user": "hola",
    "bot": "¡Hola de nuevo! ¿En qué puedo ayudarte de nuevo?",
    "timestamp": "2026-04-06T17:01:40.835Z"
  },
  {
    "id": "abc3b7e1-3ce3-42f2-944e-655b4270dd63",
    "user": "como estas",
    "bot": "🤖Lo siento, no entiendo tu mensaje. ¿Puedes reformularlo?",
    "timestamp": "2026-04-06T17:01:50.112Z"
  },
  {
    "id": "49b468b2-8878-4522-b60a-d572d1ae3b85",
    "user": "como estas?",
    "bot": "🤖Lo siento, no entiendo tu mensaje. ¿Puedes reformularlo?",
    "timestamp": "2026-04-06T17:01:57.539Z"
  },
  {
    "id": "f521e48b-9205-4992-b885-b9ed296208d5",
    "user": "como estas?",
    "bot": "🤖Lo siento, no entiendo tu mensaje. ¿Puedes reformularlo?",
    "timestamp": "2026-04-06T17:03:08.079Z"
  },
  {
    "id": "b9e06c37-fb29-4ab2-87a1-e09389edebe8",
    "user": "como estas?",
    "bot": "🤖Lo siento, no entiendo tu mensaje. ¿Puedes reformularlo?",
    "timestamp": "2026-04-06T17:03:58.436Z"
  },
  {
    "id": "f425d252-3ba6-4314-bb94-c78895cb23e6",
    "user": "como estas?",
    "bot": "🤖Lo siento, no entiendo tu mensaje. ¿Puedes reformularlo?",
    "timestamp": "2026-04-06T17:03:59.071Z"
  },
  {
    "id": "9695338e-5b2c-453e-a03a-1c874744c176",
    "user": "como estas?",
    "bot": "🤖Lo siento, no entiendo tu mensaje. ¿Puedes reformularlo?",
    "timestamp": "2026-04-06T17:07:51.158Z"
  },
  {
    "id": "1d95510a-6bd4-49fd-94d1-d48cb613d5cb",
    "user": "como estas?",
    "bot": "🤖Lo siento, no entiendo tu mensaje. ¿Puedes reformularlo?",
    "timestamp": "2026-04-06T17:07:51.874Z"
  },
  {
    "id": "f46f08db-1256-49c0-9916-9387aeadbe80",
    "user": "como estas?",
    "bot": "🤖Lo siento, no entiendo tu mensaje. ¿Puedes reformularlo?",
    "timestamp": "2026-04-06T17:07:58.561Z"
  },
  {
    "id": "b66c6918-4ad5-4b73-a64c-4dab8a8fce1f",
    "user": "hola",
    "bot": "🤖¡Hola! ¿Cómo puedo ayudarte hoy?",
    "timestamp": "2026-04-06T17:08:04.531Z"
  },
  {
    "id": "79d30aec-d467-48b9-b44a-ac3698a54c42",
    "user": "y yo",
    "bot": "🤖Lo siento, no entiendo tu mensaje. ¿Puedes reformularlo?",
    "timestamp": "2026-04-06T17:08:08.546Z"
  },
  {
    "id": "92924a85-76e6-44a9-8e90-ea8c2b741141",
    "user": "hola",
    "bot": "¡Hola de nuevo! 😄",
    "timestamp": "2026-04-06T17:08:23.481Z"
  },
  {
    "id": "6785655c-98d8-46fe-a7e5-1c53784800d8",
    "user": "como estas",
    "bot": "🤖Lo siento, no entiendo tu mensaje. ¿Puedes reformularlo?",
    "timestamp": "2026-04-06T17:08:35.569Z"
  },
  {
    "id": "8ebdc885-ef6d-4e88-bbef-a97691070dfa",
    "user": "como estas",
    "bot": "🤖Lo siento, no entiendo tu mensaje. ¿Puedes reformularlo?",
    "timestamp": "2026-04-06T17:10:43.641Z"
  },
  {
    "id": "ee2873e0-d4af-47d5-b82b-070fecf68dd1",
    "user": "como estas",
    "bot": "🤖Lo siento, no entiendo tu mensaje. ¿Puedes reformularlo?",
    "timestamp": "2026-04-06T17:10:44.421Z"
  },
  {
    "id": "2e59e204-6ffd-4c05-918f-0ceea56f0d03",
    "user": "como estas",
    "bot": "🤖Lo siento, no entiendo tu mensaje. ¿Puedes reformularlo?",
    "timestamp": "2026-04-06T17:10:45.079Z"
  },
  {
    "id": "13539eae-a557-46ca-81d4-3e7dd99ca072",
    "user": "como estas",
    "bot": "🤖Lo siento, no entiendo tu mensaje. ¿Puedes reformularlo?",
    "timestamp": "2026-04-06T17:10:45.308Z"
  },
  {
    "id": "98cae18e-03cd-4b65-b597-047ab752476a",
    "user": "como estas",
    "bot": "🤖Lo siento, no entiendo tu mensaje. ¿Puedes reformularlo?",
    "timestamp": "2026-04-06T17:10:45.470Z"
  },
  {
    "id": "4736c7a8-57a0-490a-80d1-25f4961b0b94",
    "user": "como estas",
    "bot": "🤖Lo siento, no entiendo tu mensaje. ¿Puedes reformularlo?",
    "timestamp": "2026-04-06T17:10:51.533Z"
  },
  {
    "id": "27047794-7ccb-4756-8c9d-0cee205acd2b",
    "user": "hola",
    "bot": "🤖¡Hola! ¿Cómo puedo ayudarte hoy?",
    "timestamp": "2026-04-06T17:10:56.874Z"
  },
  {
    "id": "0cc42658-7069-43a1-93a1-a69e0c54e183",
    "user": "como estas",
    "bot": "🤖Lo siento, no entiendo tu mensaje. ¿Puedes reformularlo?",
    "timestamp": "2026-04-06T17:11:01.142Z"
  },
  {
    "id": "41a528c8-cd16-47a0-9ac7-8f446ab42150",
    "user": "como estas?",
    "bot": "🤖Lo siento, no entiendo tu mensaje. ¿Puedes reformularlo?",
    "timestamp": "2026-04-06T17:11:05.116Z"
  },
  {
    "id": "3322cbea-39dc-45a8-ac66-7943dc89feb9",
    "user": "buenos dias",
    "bot": "🤖Lo siento, no entiendo tu mensaje. ¿Puedes reformularlo?",
    "timestamp": "2026-04-06T17:11:33.290Z"
  },
  {
    "id": "bbbdc024-d98c-4d57-bc62-464f169fd3cc",
    "user": "hola",
    "bot": "¡Hola de nuevo! 😄",
    "timestamp": "2026-04-06T17:11:41.713Z"
  },
  {
    "id": "b16fd343-d920-46a1-a7a1-835789504b94",
    "user": "buenos dias",
    "bot": "¡Hola de nuevo! 😄",
    "timestamp": "2026-04-06T17:13:38.203Z"
  },
  {
    "id": "4fc849d4-1d82-4096-9141-cba869c45102",
    "user": "buenas tardes",
    "bot": "¡Hola de nuevo! 😄",
    "timestamp": "2026-04-06T17:13:46.415Z"
  },
  {
    "id": "b6561678-9db8-4fe6-8a3f-3fdddd595c72",
    "user": "como estas",
    "bot": "🤖¡Estoy bien, gracias por preguntar! ¿Y tú?",
    "timestamp": "2026-04-06T17:14:01.100Z"
  },
  {
    "id": "521a8bb3-6805-4b7d-8352-b97cf5b302aa",
    "user": "como estas",
    "bot": "🤖¡Estoy bien, gracias por preguntar! ¿Y tú?",
    "timestamp": "2026-04-06T17:14:15.725Z"
  },
  {
    "id": "3ba0255a-5d0d-4f8c-81dc-009c72213069",
    "user": "como estas",
    "bot": "🤖¡Estoy bien, gracias por preguntar! ¿Y tú?",
    "timestamp": "2026-04-06T18:10:50.130Z"
  },
  {
    "id": "5b8601af-02ca-4083-8a0c-1c7fc0dacbf0",
    "user": "como estas",
    "bot": "🤖¡Estoy bien, gracias por preguntar! ¿Y tú?",
    "timestamp": "2026-04-06T18:10:58.139Z"
  },
  {
    "id": "c9df7656-55b0-4c33-b26c-28680ed53f85",
    "user": "como estas",
    "bot": "🤖¡Estoy bien, gracias por preguntar! ¿Y tú?",
    "timestamp": "2026-04-06T18:13:25.636Z"
  },
  {
    "id": "ff48cf4f-02a1-4a10-b563-b8f91218f5ec",
    "user": "como estas",
    "bot": "🤖¡Estoy bien, gracias por preguntar! ¿Y tú?",
    "timestamp": "2026-04-06T18:13:37.574Z"
  },
  {
    "id": "28daffec-8832-4703-8f39-7344b849e39e",
    "user": "como estas",
    "bot": "🤖¡Estoy bien, gracias por preguntar! ¿Y tú?",
    "timestamp": "2026-04-07T01:26:01.286Z"
  },
  {
    "id": "51c89577-7b63-43d3-8b96-91ab801b4e52",
    "user": "como estas",
    "bot": "🤖¡Estoy bien, gracias por preguntar! ¿Y tú?",
    "timestamp": "2026-04-07T01:26:18.741Z"
  },
  {
    "id": "282a9cdd-cde1-4df8-b8ef-f9795670e26f",
    "user": "como estas",
    "bot": "🤖¡Estoy bien, gracias por preguntar! ¿Y tú?",
    "timestamp": "2026-04-07T01:34:34.489Z"
  },
  {
    "id": "6edc2b06-ea32-4169-bd6f-15c170a3ace6",
    "user": "como estas",
    "bot": "🤖¡Estoy bien, gracias por preguntar! ¿Y tú?",
    "timestamp": "2026-04-07T06:40:03.224Z"
  },
  {
    "id": "eb06c718-1133-430f-9e94-9b8ff4be7ac1",
    "user": "hola",
    "bot": "🤖¡Hola! ¿Cómo puedo ayudarte hoy?",
    "timestamp": "2026-04-07T06:40:09.202Z"
  },
  {
    "id": "7636c2df-7b2d-469a-8c88-837f52743302",
    "user": "hola",
    "bot": "¡Hola de nuevo! 😄",
    "timestamp": "2026-04-07T19:37:38.672Z"
  },
  {
    "id": "075f681e-4a9e-4729-b913-546849db6731",
    "user": "hola",
    "bot": "¡Hola de nuevo! 😄",
    "timestamp": "2026-04-07T19:37:40.280Z"
  },
  {
    "id": "f5696fb8-5142-4be6-8b95-430d7142e09f",
    "user": "como estas",
    "bot": "🤖¡Estoy bien, gracias por preguntar! ¿Y tú?",
    "timestamp": "2026-04-07T19:37:44.282Z"
  },
  {
    "id": "1ca9511e-6748-46e6-bfd8-1f3851147b0b",
    "user": "hola",
    "bot": "¡Hola de nuevo! 😄",
    "timestamp": "2026-04-07T20:22:35.120Z"
  },
  {
    "id": "67c3a129-6c10-46b9-84a5-0909bb9faa00",
    "user": "hola",
    "bot": "¡Hola de nuevo! 😄",
    "timestamp": "2026-04-07T20:22:36.477Z"
  },
  {
    "id": "6cae41b4-8025-41d7-bf1d-eada9a8d5b3c",
    "user": "hola",
    "bot": "¡Hola de nuevo! 😄",
    "timestamp": "2026-04-07T20:22:36.938Z"
  },
  {
    "id": "6bef47ea-1b7f-419f-aac2-75109a2d96b9",
    "user": "hola",
    "bot": "¡Hola de nuevo! 😄",
    "timestamp": "2026-04-07T21:03:52.616Z"
  },
  {
    "id": "9fe42181-e257-4a1f-9d78-d7a8a136cbc5",
    "user": "Me llamo Rich",
    "bot": "¡Encantado de conocerte, rich! 😄",
    "timestamp": "2026-04-07T21:04:19.913Z"
  },
  {
    "id": "b01d128c-47a6-470a-ab78-6a97c26b08d3",
    "user": "como me llamo?",
    "bot": "¡Encantado de conocerte, ?! 😄",
    "timestamp": "2026-04-07T21:04:42.800Z"
  },
  {
    "id": "2517cc3e-5d0c-40cc-ba99-b472d6ed48a2",
    "user": "como me llamo",
    "bot": "No entendí tu nombre 🤔",
    "timestamp": "2026-04-07T21:04:48.934Z"
  },
  {
    "id": "ea6702e0-705d-4a8d-8a1b-19d6ccf67e7c",
    "user": "me llamo rich",
    "bot": "¡Encantado de conocerte, rich! 😄",
    "timestamp": "2026-04-07T21:04:57.099Z"
  },
  {
    "id": "0643400e-8635-43c9-b47d-9d1628175e97",
    "user": "como me llamo",
    "bot": "No entendí tu nombre 🤔",
    "timestamp": "2026-04-07T21:05:03.381Z"
  },
  {
    "id": "bb49f9ad-1a48-4a85-ad9d-e8961f0bb907",
    "user": "como estas",
    "bot": "🤖 Estoy bien 😄 ¿Y tú?",
    "timestamp": "2026-04-07T21:05:12.207Z"
  },
  {
    "id": "1eb329a8-26f7-431c-af8f-ecbc3f2c6952",
    "user": "y yo",
    "bot": "¡Seguro estás bien también! 😄",
    "timestamp": "2026-04-07T21:05:18.620Z"
  },
  {
    "id": "352ec10b-9bf9-4cb8-a3c5-2e0b4820ee31",
    "user": "hola",
    "bot": "🤖 ¡Hola! ¿Cómo puedo ayudarte hoy?",
    "timestamp": "2026-04-07T21:08:21.391Z"
  },
  {
    "id": "0accca16-e0a5-4103-b9f2-2e8a14d04e9c",
    "user": "como me llamo",
    "bot": "Aún no me has dicho tu nombre 🤔",
    "timestamp": "2026-04-07T21:08:26.865Z"
  },
  {
    "id": "3d4bf164-fe2b-4435-9748-835c0b544f01",
    "user": "me llamo ruch",
    "bot": "¡Encantado de conocerte, ruch! 😄",
    "timestamp": "2026-04-07T21:08:34.964Z"
  },
  {
    "id": "65e10902-ec07-4a4c-9d6f-ee40dfe59dd3",
    "user": "como me llamo",
    "bot": "Te llamas ruch 😏",
    "timestamp": "2026-04-07T21:08:40.727Z"
  },
  {
    "id": "fff7f319-e446-4a6a-838e-d649234daa12",
    "user": "como me llamo?",
    "bot": "Aún no me has dicho tu nombre 🤔",
    "timestamp": "2026-04-07T21:08:45.836Z"
  },
  {
    "id": "240ee4ae-d0b7-4345-8212-865115eac607",
    "user": "hola",
    "bot": "¡Hola de nuevo! 😄",
    "timestamp": "2026-04-07T21:11:39.321Z"
  },
  {
    "id": "70b0cefa-2c74-48c1-91cc-065355d4c561",
    "user": "como me llamo?",
    "bot": "Te llamas ? 😏",
    "timestamp": "2026-04-07T21:11:46.402Z"
  },
  {
    "id": "0f7f7187-c50e-42bc-b38a-5b63c2f34e71",
    "user": "como me llamo",
    "bot": "Te llamas ? 😏",
    "timestamp": "2026-04-07T21:11:50.848Z"
  },
  {
    "id": "dbea5c4a-01e7-4988-897a-6be9766d4612",
    "user": "no",
    "bot": "🤖 No entendí eso aún, pero estoy aprendiendo 😄",
    "timestamp": "2026-04-07T21:11:55.208Z"
  },
  {
    "id": "a9a6c92a-9113-4cb0-a28d-408ada64b7df",
    "user": "me llamo Rich",
    "bot": "¡Encantado de conocerte, rich! 😄",
    "timestamp": "2026-04-07T21:12:01.752Z"
  },
  {
    "id": "f8cca0c6-91e4-4d50-8291-420a3c49713c",
    "user": "como me llamo",
    "bot": "Te llamas Rich 😏",
    "timestamp": "2026-04-07T21:12:07.299Z"
  },
  {
    "id": "0210f676-cffe-48d2-936b-18aa8358095e",
    "user": "hola?",
    "bot": "🤖 ¡Hola! ¿Cómo puedo ayudarte hoy?",
    "timestamp": "2026-04-07T21:12:27.998Z"
  },
  {
    "id": "a58923c8-7808-4228-af10-1716ff55bdce",
    "user": "como me llamo?",
    "bot": "Aún no me has dicho tu nombre 🤔",
    "timestamp": "2026-04-07T21:13:16.362Z"
  },
  {
    "id": "35e1a493-35cb-47ba-b32a-2b5c19a15a3c",
    "user": "rich",
    "bot": "🤖 No entendí eso aún, pero estoy aprendiendo 😄",
    "timestamp": "2026-04-07T21:13:28.622Z"
  },
  {
    "id": "150c2505-0c1e-480b-bb1f-ff1dc97513c9",
    "user": "hola",
    "bot": "¡Hola de nuevo! 😄",
    "timestamp": "2026-04-07T21:13:33.064Z"
  },
  {
    "id": "6d5a5a73-be76-48cb-92c2-dc17d26801d2",
    "user": "como me llamo?",
    "bot": "Te llamas ? 😏",
    "timestamp": "2026-04-07T21:13:39.013Z"
  },
  {
    "id": "491f3591-d51e-4386-913b-636ce37066c0",
    "user": "como me llamo?",
    "bot": "Te llamas ? 😏",
    "timestamp": "2026-04-07T21:16:19.969Z"
  },
  {
    "id": "9602a148-5235-412e-b728-24ff35140366",
    "user": "hola",
    "bot": "¡Hola de nuevo! 😄",
    "timestamp": "2026-04-07T21:16:23.427Z"
  },
  {
    "id": "f6c3363b-c3c8-435d-bdea-8e86d5c82672",
    "user": "como me llamo?",
    "bot": "Te llamas ? 😏",
    "timestamp": "2026-04-07T21:16:28.183Z"
  },
  {
    "id": "9b83e20d-a6d6-4881-8f4e-baae8e706a99",
    "user": "como me llamo?",
    "bot": "Te llamas ? 😏",
    "timestamp": "2026-04-07T21:18:22.197Z"
  },
  {
    "id": "0c66f50d-814c-484d-a89e-d31ae7b043e8",
    "user": "como me llamo?",
    "bot": "Te llamas ? 😏",
    "timestamp": "2026-04-07T21:19:02.705Z"
  },
  {
    "id": "f32f36aa-dbd4-44fa-aa46-b540407d983d",
    "user": "como me llamo?",
    "bot": "Te llamas ? 😏",
    "timestamp": "2026-04-07T21:19:16.456Z"
  },
  {
    "id": "1a763831-ddf9-400a-95e5-298f135a03fa",
    "user": "hola",
    "bot": "¡Hola de nuevo! 😄",
    "timestamp": "2026-04-07T21:19:47.760Z"
  },
  {
    "id": "414498e3-7300-479a-a221-d07e788d888f",
    "user": "me llamo rich",
    "bot": "¡Encantado de conocerte, rich! 😄",
    "timestamp": "2026-04-07T21:19:52.797Z"
  },
  {
    "id": "87441b85-ff09-4f61-87be-ef90655fdab8",
    "user": "como me llamo?",
    "bot": "Te llamas rich 😏",
    "timestamp": "2026-04-07T21:20:00.046Z"
  },
  {
    "id": "21ce9be1-ddfd-4954-add4-5a53fa94d981",
    "user": "como me llamo?",
    "bot": "Te llamas ? 😏",
    "timestamp": "2026-04-07T21:20:02.023Z"
  }
]